{"paths":{"0":["loading/titlelog1",2],"1":["agreement/agreement",2],"2":["tip/texture/ad",2],"3":["tip/texture/closebuttonv3-80px",2],"4":["loading/titlelog",2],"5":["texture/chatbubble",1,1],"6":["agreement/textures/di2",1,1],"7":["dialog/DialogItemView",0],"8":["agreement/textures/ad-text",1,1],"9":["loading/img_ui_coincollector_progress_bar_fill",1,1],"10":["tip/prefab/ToastView",0],"11":["agreement/agreement",1,1],"12":["texture/img_ui_storyprogress_diegetic_star_bubble",1,1],"15":["data/slot_info",4],"16":["texture/finger",1,1],"17":["agreement/textures/mask",1,1],"18":["data/redtip_info",4],"19":["agreement/textures/ad-close",1,1],"20":["loading/LoadingView",0],"21":["agreement/textures/AutoAtlas",3],"22":["data/game_lang_zh",4],"23":["tip/texture/ad",1,1],"24":["loading/titlelog",1,1],"25":["tip/texture/booster_title_bg",1,1],"27":["agreement/textures/ad-btn-bg",1,1],"35":["tip/texture/booster_title_bg",2],"36":["loading/img_ui_coincollector_progress_bar_bg",2],"37":["tip/texture/cion_icon",2],"38":["loading/img_ui_coincollector_progress_bar_fill",2],"39":["texture/AutoAtlas",3],"40":["loading/img_ui_coincollector_progress_bar_bg",1,1],"41":["agreement/PrivacyPopView",0],"42":["data/guide_config",4],"43":["texture/chatheadbackgroundshape",1,1],"45":["agreement/textures/btn1",1,1],"46":["data/Administrator",4],"47":["texture/play_small",1,1],"48":["loading/titlelog1",1,1],"50":["texture/booster_title_bg",1,1],"51":["tip/texture/closebuttonv3-80px",1,1],"52":["loading/LoginView",0],"53":["data/games_info",4],"55":["data/game_info",4],"56":["texture/Amelia-Happy-side",1,1],"57":["agreement/textures/xl",1,1],"59":["data/activity_info",4],"60":["agreement/textures/ad-box",1,1],"61":["agreement/PrivacyView",0],"62":["tip/prefab/TipView",0],"63":["tip/texture/cion_icon",1,1]},"types":["cc.Prefab","cc.SpriteFrame","cc.Texture2D","cc.SpriteAtlas","cc.JsonAsset"],"uuids":["22Jh6+++NMT6rZHpOoCo/7","40TMY1KLBEPLns+0h/N5Xz","4d+8wMOfVPTIfgdgL4kjxO","54TvyY1LpFNLnhc1MOZZv0","7bACThTxFAWJANr0xBpC/g","01anCIxodJuaJhveBDX0pj","01ohCZkypGWYd6gucVSrYn","03+S1be6JNx65aaR9FNI5i","07563UuK9Gf7+UgZ4DiZIl","0dMccPbQ1GCLpeSmAuSzyb","0dypWvIkdP2oGjvLniIRI7","0e2e0x7CJPPKYQB1AD9aqH","16ChXIs7BI5qtfVP9rgAkO","1b1f9fd9e","1c08df95e","22QndPdZRMxI0zmNQfchRX","24mgelFJtIZZuD+9fg/BaR","28HfCLoJRMr5/dfJnqeBM3","2a1QI0lY5LGrSWrz3KM3/6","39CgtSnYBFQYwOBcN/GNQi","397acIc65PcJv6Z7fRZObn","3b6NHtNv9KSY9NdKsKy5df","45SsqzmTpB0rptZl+KVbqm","4bEKlg2a5M4J9anMAfUMMg","53EuovKQVDN7AxLVKj3Y4D","63WQN2pPNKrLnJOneT5wJg","6bLJhxOZhOoYWNT8iyt3WS","6d6bc5yG1MoI0cDYYfZqmI","71VhFCTINJM6/Ky3oX9nBT","02delMVqdBD70a/HSD99FK","0b9Eh7/c5DmZ+UOqQXYUZC","18Fi3Zka1M+JtN7s3VlDvG","1bRnX3BLZMhpI4BzmrceCR","29FYIk+N1GYaeWH/q1NxQO","46Un0wIzxKqI7UbCt8pWYy","9dkIq4qJpKibeQLvbyQwcj","aapkBO2b1LOaqaw6IieK7i","afAS7x/JNCW6W0ECk6ZQ78","calGTc/VBHrZCjb7XzuR+1","4ccdzyVLpK9Y5VyVj5I6lz","62ZzMQa7NMNLjOnKVP5VSG","8b84QBGodIqrx3ujsoGGEt","8b+5HswMVHwJ1ToQjJzNSq","8cTHeXVj1JzIjmpPYVLQvy","92AMC3OMFH6q/KsHTcPwJm","95w6rtL+lGnoHmfwJoZJdN","9dR3sj8ltClKI1UIObqHJd","aboLjtYQxKZ6/IvBqCvlMv","adnFwSZDJDDLxaJ6NtDfDN","b4P/PCArtIdIH38t6mlw8Y","beVQC6PHxE1p26To5YhVl9","c8OkmXTZ5EeLTNNvN5TVsK","d5kScj/NdFlJtd05GMFSy0","d6yHkLhNFE+YV+oTzJdpjK","d8HsitJHxOYqo801xBk8ev","e1VqJT0qxJVq7wp7dhuezo","e7jIGq35JDJ4anPnEqp0IC","e7+GYEI9hCzb/SGRPVNdz5","e8Ueib+qJEhL6mXAHdnwbi","f2JZZ7GGZD56xbOywimiSE","f3CXUWnhdCK4Un3c+bxvkA","f7YKXEskhLspWgKBHOMgNM","faNPWkR3NK/Ib31s9Il1BK","febp/R6apLNor/g0v2QbI9","9bvaMerUlDyary99mJa6xp","a2MjXRFdtLlYQ5ouAFv/+R","b7RzT/79pPdInDcBq+wZWW","c2LKBJSRdO0pFwBCdYRGwF","e97GVMl6JHh5Ml5qEDdSGa","ecpdLyjvZBwrvm+cedCcQy","f0BIwQ8D5Ml7nTNQbh1YlS"],"scenes":{},"redirect":[29,0,69,0],"deps":["internal"],"packs":{"022298220":[5,7,43,50],"02648e782":[11,61],"031c76638":[48,67],"03a678077":[30,31,23,66,62,63],"04fef62db":[19,41,64],"065c3b51a":[13,14,0,1,2,3,26,28,4,44,35,36,37,49,38,54,58],"06d6b9255":[9,20,40],"072f21375":[10,25],"0a3d5e70e":[47,52],"0c339d10f":[33,68,70]},"name":"resources","importBase":"import","nativeBase":"native","debug":false,"isZip":false,"encrypted":false,"versions":{"import":[6,"dd842","022298220","38f3b","02648e782","f6897","031c76638","4eacb","03a678077","d132e","04fef62db","2da43","065c3b51a","7c5e4","06d6b9255","ac424","072f21375","c2b57",8,"1bb3d","0a3d5e70e","54be9","0c339d10f","a9ccb",12,"e01b8",15,"c4019",16,"d39a1",17,"69c1d",18,"d4413",21,"720f5",22,"43dfd",39,"c3b6f",24,"2f5d1",27,"611f3",42,"1b716",45,"6b606",46,"97026",65,"43d76",51,"82f1a",53,"531b9",55,"53721",56,"02189",57,"721c5",59,"4b5f3",60,"b7704"],"native":[13,"fa2d5",14,"9af2c",0,"5f274",1,"88e25",2,"fc339",3,"77a35",26,"687a4",28,"c06a9",4,"51f51",44,"210dd",35,"b05af",36,"1850c",37,"ab1bc",49,"83fcc",38,"9b37f",54,"cdbc9",58,"90cf4"]}}